cbox/__init__.py
cbox/cli.py
cbox/gui.py
cbox/i18n.py
cbox/mybox.py
cbox_tool-0.1.14.dist-info/METADATA
cbox_tool-0.1.14.dist-info/WHEEL
cbox_tool-0.1.14.dist-info/entry_points.txt
cbox_tool-0.1.14.dist-info/top_level.txt
cbox_tool-0.1.14.dist-info/RECORD
