Metadata-Version: 2.1
Name: cbox-tool
Version: 0.1.14
Summary: A powerful multi-repository management tool for Git projects
Home-page: https://github.com/Beliefei/cbox
Author: belief
Author-email: beliefchinese@gmail.com
Project-URL: Bug Tracker, https://github.com/Beliefei/cbox/issues
Project-URL: Documentation, https://github.com/Beliefei/cbox/tree/main/docs
Project-URL: Source Code, https://github.com/Beliefei/cbox
Keywords: git repository management tool workspace
Classifier: Programming Language :: Python :: 3
Classifier: License :: OSI Approved :: MIT License
Classifier: Operating System :: OS Independent
Classifier: Topic :: Software Development :: Version Control
Classifier: Topic :: Utilities
Requires-Python: >=3.8
Requires-Dist: click>=8.0.0
Requires-Dist: pyyaml>=6.0.0
Requires-Dist: rich>=13.0.0
Requires-Dist: gitpython>=3.1.0
Requires-Dist: PySide6>=6.6.0
